odoo/addons/project_task_analytic_propagation/README.rst
odoo/addons/project_task_analytic_propagation/__init__.py
odoo/addons/project_task_analytic_propagation/__manifest__.py
odoo/addons/project_task_analytic_propagation/i18n/it.po
odoo/addons/project_task_analytic_propagation/i18n/project_task_analytic_propagation.pot
odoo/addons/project_task_analytic_propagation/i18n/pt_BR.po
odoo/addons/project_task_analytic_propagation/models/__init__.py
odoo/addons/project_task_analytic_propagation/models/account_analytic_line.py
odoo/addons/project_task_analytic_propagation/models/project_task.py
odoo/addons/project_task_analytic_propagation/readme/CONFIGURE.md
odoo/addons/project_task_analytic_propagation/readme/CONTRIBUTORS.md
odoo/addons/project_task_analytic_propagation/readme/DESCRIPTION.md
odoo/addons/project_task_analytic_propagation/readme/USAGE.md
odoo/addons/project_task_analytic_propagation/static/description/icon.png
odoo/addons/project_task_analytic_propagation/static/description/index.html
odoo/addons/project_task_analytic_propagation/tests/__init__.py
odoo/addons/project_task_analytic_propagation/tests/test_hr_timesheet.py
odoo/addons/project_task_analytic_propagation/views/project_task_views.xml
odoo_addon_project_task_analytic_propagation-18.0.1.0.1.dist-info/METADATA
odoo_addon_project_task_analytic_propagation-18.0.1.0.1.dist-info/WHEEL
odoo_addon_project_task_analytic_propagation-18.0.1.0.1.dist-info/top_level.txt
odoo_addon_project_task_analytic_propagation-18.0.1.0.1.dist-info/RECORD
